{
  "annotations": {
    "list": [
      {
        "builtIn": 1,
        "datasource": "-- Grafana --",
        "enable": true,
        "hide": true,
        "iconColor": "rgba(0, 211, 255, 1)",
        "name": "Annotations & Alerts",
        "type": "dashboard"
      }
    ]
  },
  "editable": true,
  "gnetId": null,
  "graphTooltip": 0,
  "id": 22,
  "iteration": 1640450987650,
  "links": [
    {
      "asDropdown": true,
      "icon": "external link",
      "keepTime": true,
      "tags": [
        "system"
      ],
      "title": "System Dashboards",
      "type": "dashboards"
    }
  ],
  "panels": [
    {
      "collapsed": false,
      "datasource": null,
      "gridPos": {
        "h": 1,
        "w": 24,
        "x": 0,
        "y": 0
      },
      "id": 49,
      "panels": [],
      "title": "CPU - User / System",
      "type": "row"
    },
    {
      "aliasColors": {},
      "bars": false,
      "dashLength": 10,
      "dashes": false,
      "datasource": null,
      "editable": true,
      "error": false,
      "fill": 0,
      "fillGradient": 0,
      "grid": {},
      "gridPos": {
        "h": 7,
        "w": 12,
        "x": 0,
        "y": 1
      },
      "hiddenSeries": false,
      "id": 3,
      "isNew": true,
      "legend": {
        "avg": false,
        "current": false,
        "max": false,
        "min": false,
        "show": false,
        "total": false,
        "values": false
      },
      "lines": true,
      "linewidth": 2,
      "links": [],
      "nullPointMode": "connected",
      "options": {
        "dataLinks": []
      },
      "percentage": false,
      "pointradius": 5,
      "points": false,
      "renderer": "flot",
      "seriesOverrides": [],
      "spaceLength": 10,
      "stack": false,
      "steppedLine": false,
      "targets": [
        {
          "aggregator": "avg",
          "app": "HOST",
          "downsampleAggregator": "avg",
          "errors": {},
          "metric": "cpu_user",
          "precision": "default",
          "refId": "B",
          "templatedHost": ""
        }
      ],
      "thresholds": [],
      "timeFrom": null,
      "timeRegions": [],
      "timeShift": null,
      "title": "CPU Utilization - User",
      "tooltip": {
        "shared": false,
        "sort": 0,
        "value_type": "individual"
      },
      "type": "graph",
      "xaxis": {
        "buckets": null,
        "mode": "time",
        "name": null,
        "show": true,
        "values": []
      },
      "yaxes": [
        {
          "format": "percent",
          "logBase": 1,
          "max": null,
          "min": null,
          "show": true
        },
        {
          "format": "short",
          "logBase": 1,
          "max": null,
          "min": null,
          "show": true
        }
      ],
      "yaxis": {
        "align": false,
        "alignLevel": null
      }
    },
    {
      "aliasColors": {},
      "bars": false,
      "dashLength": 10,
      "dashes": false,
      "datasource": null,
      "editable": true,
      "error": false,
      "fill": 0,
      "fillGradient": 0,
      "grid": {},
      "gridPos": {
        "h": 7,
        "w": 12,
        "x": 12,
        "y": 1
      },
      "hiddenSeries": false,
      "id": 28,
      "isNew": true,
      "legend": {
        "avg": false,
        "current": false,
        "max": false,
        "min": false,
        "show": false,
        "total": false,
        "values": false
      },
      "lines": true,
      "linewidth": 2,
      "links": [],
      "nullPointMode": "connected",
      "options": {
        "dataLinks": []
      },
      "percentage": false,
      "pointradius": 5,
      "points": false,
      "renderer": "flot",
      "seriesOverrides": [],
      "spaceLength": 10,
      "stack": false,
      "steppedLine": false,
      "targets": [
        {
          "aggregator": "avg",
          "app": "HOST",
          "downsampleAggregator": "avg",
          "errors": {},
          "hide": false,
          "hosts": "",
          "metric": "cpu_system",
          "precision": "default",
          "refId": "A",
          "templatedHost": ""
        }
      ],
      "thresholds": [],
      "timeFrom": null,
      "timeRegions": [],
      "timeShift": null,
      "title": "CPU Utilization - System",
      "tooltip": {
        "shared": false,
        "sort": 0,
        "value_type": "individual"
      },
      "type": "graph",
      "xaxis": {
        "buckets": null,
        "mode": "time",
        "name": null,
        "show": true,
        "values": []
      },
      "yaxes": [
        {
          "format": "percent",
          "logBase": 1,
          "max": null,
          "min": null,
          "show": true
        },
        {
          "format": "short",
          "logBase": 1,
          "max": null,
          "min": null,
          "show": true
        }
      ],
      "yaxis": {
        "align": false,
        "alignLevel": null
      }
    },
    {
      "collapsed": true,
      "datasource": null,
      "gridPos": {
        "h": 1,
        "w": 24,
        "x": 0,
        "y": 8
      },
      "id": 50,
      "panels": [
        {
          "aliasColors": {},
          "bars": false,
          "datasource": null,
          "editable": true,
          "error": false,
          "fill": 0,
          "grid": {},
          "gridPos": {
            "h": 7,
            "w": 12,
            "x": 0,
            "y": 9
          },
          "id": 29,
          "isNew": true,
          "legend": {
            "avg": false,
            "current": false,
            "max": false,
            "min": false,
            "show": false,
            "total": false,
            "values": false
          },
          "lines": true,
          "linewidth": 2,
          "links": [],
          "nullPointMode": "connected",
          "percentage": false,
          "pointradius": 5,
          "points": false,
          "renderer": "flot",
          "seriesOverrides": [],
          "stack": false,
          "steppedLine": false,
          "targets": [
            {
              "aggregator": "avg",
              "app": "HOST",
              "downsampleAggregator": "avg",
              "errors": {},
              "metric": "cpu_nice",
              "precision": "default",
              "refId": "F",
              "templatedHost": ""
            }
          ],
          "thresholds": [],
          "timeFrom": null,
          "timeShift": null,
          "title": "CPU Utilization - Nice",
          "tooltip": {
            "shared": false,
            "value_type": "individual"
          },
          "type": "graph",
          "xaxis": {
            "show": true
          },
          "yaxes": [
            {
              "format": "percent",
              "logBase": 1,
              "max": null,
              "min": null,
              "show": true
            },
            {
              "format": "short",
              "logBase": 1,
              "max": null,
              "min": null,
              "show": true
            }
          ]
        },
        {
          "aliasColors": {},
          "bars": false,
          "datasource": null,
          "editable": true,
          "error": false,
          "fill": 0,
          "grid": {},
          "gridPos": {
            "h": 7,
            "w": 12,
            "x": 12,
            "y": 9
          },
          "id": 30,
          "isNew": true,
          "legend": {
            "avg": false,
            "current": false,
            "max": false,
            "min": false,
            "show": false,
            "total": false,
            "values": false
          },
          "lines": true,
          "linewidth": 2,
          "links": [],
          "nullPointMode": "connected",
          "percentage": false,
          "pointradius": 5,
          "points": false,
          "renderer": "flot",
          "seriesOverrides": [],
          "stack": false,
          "steppedLine": false,
          "targets": [
            {
              "aggregator": "avg",
              "app": "HOST",
              "downsampleAggregator": "avg",
              "errors": {},
              "metric": "cpu_idle",
              "precision": "default",
              "refId": "C",
              "templatedHost": ""
            }
          ],
          "thresholds": [],
          "timeFrom": null,
          "timeShift": null,
          "title": "CPU Utilization - Idle",
          "tooltip": {
            "shared": false,
            "value_type": "individual"
          },
          "type": "graph",
          "xaxis": {
            "show": true
          },
          "yaxes": [
            {
              "format": "percent",
              "logBase": 1,
              "max": null,
              "min": null,
              "show": true
            },
            {
              "format": "short",
              "logBase": 1,
              "max": null,
              "min": null,
              "show": true
            }
          ]
        }
      ],
      "title": "CPU - Nice / Idle",
      "type": "row"
    },
    {
      "collapsed": true,
      "datasource": null,
      "gridPos": {
        "h": 1,
        "w": 24,
        "x": 0,
        "y": 9
      },
      "id": 51,
      "panels": [
        {
          "aliasColors": {},
          "bars": false,
          "datasource": null,
          "editable": true,
          "error": false,
          "fill": 0,
          "grid": {},
          "gridPos": {
            "h": 7,
            "w": 12,
            "x": 0,
            "y": 10
          },
          "id": 31,
          "isNew": true,
          "legend": {
            "avg": false,
            "current": false,
            "max": false,
            "min": false,
            "show": false,
            "total": false,
            "values": false
          },
          "lines": true,
          "linewidth": 2,
          "links": [],
          "nullPointMode": "connected",
          "percentage": false,
          "pointradius": 5,
          "points": false,
          "renderer": "flot",
          "seriesOverrides": [],
          "stack": false,
          "steppedLine": false,
          "targets": [
            {
              "aggregator": "avg",
              "app": "HOST",
              "downsampleAggregator": "avg",
              "errors": {},
              "metric": "cpu_wio",
              "precision": "default",
              "refId": "E",
              "templatedHost": ""
            }
          ],
          "thresholds": [],
          "timeFrom": null,
          "timeShift": null,
          "title": "CPU Utilization - iowait",
          "tooltip": {
            "shared": false,
            "value_type": "individual"
          },
          "type": "graph",
          "xaxis": {
            "show": true
          },
          "yaxes": [
            {
              "format": "percent",
              "logBase": 1,
              "max": null,
              "min": null,
              "show": true
            },
            {
              "format": "short",
              "logBase": 1,
              "max": null,
              "min": null,
              "show": true
            }
          ]
        },
        {
          "aliasColors": {},
          "bars": false,
          "datasource": null,
          "editable": true,
          "error": false,
          "fill": 0,
          "grid": {},
          "gridPos": {
            "h": 7,
            "w": 12,
            "x": 12,
            "y": 10
          },
          "id": 32,
          "isNew": true,
          "legend": {
            "avg": false,
            "current": false,
            "max": false,
            "min": false,
            "show": false,
            "total": false,
            "values": false
          },
          "lines": true,
          "linewidth": 2,
          "links": [],
          "nullPointMode": "connected",
          "percentage": false,
          "pointradius": 5,
          "points": false,
          "renderer": "flot",
          "seriesOverrides": [],
          "stack": false,
          "steppedLine": false,
          "targets": [
            {
              "aggregator": "avg",
              "app": "HOST",
              "downsampleAggregator": "avg",
              "errors": {},
              "metric": "cpu_intr",
              "precision": "default",
              "refId": "D",
              "templatedHost": ""
            }
          ],
          "thresholds": [],
          "timeFrom": null,
          "timeShift": null,
          "title": "CPU Utilization - Hardware Interrupt",
          "tooltip": {
            "shared": false,
            "value_type": "individual"
          },
          "type": "graph",
          "xaxis": {
            "show": true
          },
          "yaxes": [
            {
              "format": "percent",
              "logBase": 1,
              "max": null,
              "min": null,
              "show": true
            },
            {
              "format": "short",
              "logBase": 1,
              "max": null,
              "min": null,
              "show": true
            }
          ]
        }
      ],
      "title": "CPU - Iowait / Intr",
      "type": "row"
    },
    {
      "collapsed": true,
      "datasource": null,
      "gridPos": {
        "h": 1,
        "w": 24,
        "x": 0,
        "y": 10
      },
      "id": 52,
      "panels": [
        {
          "aliasColors": {},
          "bars": false,
          "datasource": null,
          "editable": true,
          "error": false,
          "fill": 0,
          "grid": {},
          "gridPos": {
            "h": 7,
            "w": 12,
            "x": 0,
            "y": 11
          },
          "id": 33,
          "isNew": true,
          "legend": {
            "avg": false,
            "current": false,
            "max": false,
            "min": false,
            "show": false,
            "total": false,
            "values": false
          },
          "lines": true,
          "linewidth": 2,
          "links": [],
          "nullPointMode": "connected",
          "percentage": false,
          "pointradius": 5,
          "points": false,
          "renderer": "flot",
          "seriesOverrides": [],
          "stack": false,
          "steppedLine": false,
          "targets": [
            {
              "aggregator": "avg",
              "app": "HOST",
              "downsampleAggregator": "avg",
              "errors": {},
              "metric": "cpu_sintr",
              "precision": "default",
              "refId": "G",
              "templatedHost": ""
            }
          ],
          "thresholds": [],
          "timeFrom": null,
          "timeShift": null,
          "title": "CPU Utilization - Software Interrupt",
          "tooltip": {
            "shared": false,
            "value_type": "individual"
          },
          "type": "graph",
          "xaxis": {
            "show": true
          },
          "yaxes": [
            {
              "format": "percent",
              "logBase": 1,
              "max": null,
              "min": null,
              "show": true
            },
            {
              "format": "short",
              "logBase": 1,
              "max": null,
              "min": null,
              "show": true
            }
          ]
        },
        {
          "aliasColors": {},
          "bars": false,
          "datasource": null,
          "editable": true,
          "error": false,
          "fill": 0,
          "grid": {},
          "gridPos": {
            "h": 7,
            "w": 12,
            "x": 12,
            "y": 11
          },
          "id": 34,
          "isNew": true,
          "legend": {
            "avg": false,
            "current": false,
            "max": false,
            "min": false,
            "show": false,
            "total": false,
            "values": false
          },
          "lines": true,
          "linewidth": 2,
          "links": [],
          "nullPointMode": "connected",
          "percentage": false,
          "pointradius": 5,
          "points": false,
          "renderer": "flot",
          "seriesOverrides": [],
          "stack": false,
          "steppedLine": false,
          "targets": [
            {
              "aggregator": "avg",
              "app": "HOST",
              "downsampleAggregator": "avg",
              "errors": {},
              "metric": "cpu_steal",
              "precision": "default",
              "refId": "H",
              "templatedHost": ""
            }
          ],
          "thresholds": [],
          "timeFrom": null,
          "timeShift": null,
          "title": "CPU Utilization - Steal (VM)",
          "tooltip": {
            "shared": false,
            "value_type": "individual"
          },
          "type": "graph",
          "xaxis": {
            "show": true
          },
          "yaxes": [
            {
              "format": "percent",
              "logBase": 1,
              "max": null,
              "min": null,
              "show": true
            },
            {
              "format": "short",
              "logBase": 1,
              "max": null,
              "min": null,
              "show": true
            }
          ]
        }
      ],
      "title": "CPU - SoftIntr / Steal",
      "type": "row"
    },
    {
      "collapsed": true,
      "datasource": null,
      "gridPos": {
        "h": 1,
        "w": 24,
        "x": 0,
        "y": 11
      },
      "id": 53,
      "panels": [
        {
          "aliasColors": {},
          "bars": false,
          "datasource": null,
          "editable": true,
          "error": false,
          "fill": 0,
          "grid": {},
          "gridPos": {
            "h": 7,
            "w": 24,
            "x": 0,
            "y": 12
          },
          "id": 5,
          "isNew": true,
          "legend": {
            "avg": false,
            "current": false,
            "max": false,
            "min": false,
            "show": false,
            "total": false,
            "values": false
          },
          "lines": true,
          "linewidth": 2,
          "links": [],
          "nullPointMode": "connected",
          "percentage": false,
          "pointradius": 5,
          "points": false,
          "renderer": "flot",
          "seriesOverrides": [],
          "stack": false,
          "steppedLine": false,
          "targets": [
            {
              "aggregator": "avg",
              "alias": "load_one_minute",
              "app": "HOST",
              "downsampleAggregator": "avg",
              "errors": {},
              "metric": "load_one",
              "precision": "default",
              "refId": "A",
              "templatedHost": ""
            }
          ],
          "thresholds": [],
          "timeFrom": null,
          "timeShift": null,
          "title": "System Load Average - 1 Minute",
          "tooltip": {
            "shared": false,
            "value_type": "cumulative"
          },
          "type": "graph",
          "xaxis": {
            "show": true
          },
          "yaxes": [
            {
              "format": "short",
              "logBase": 1,
              "max": null,
              "min": null,
              "show": true
            },
            {
              "format": "short",
              "logBase": 1,
              "max": null,
              "min": null,
              "show": true
            }
          ]
        }
      ],
      "title": "System Load - 1 Minute",
      "type": "row"
    },
    {
      "collapsed": true,
      "datasource": null,
      "gridPos": {
        "h": 1,
        "w": 24,
        "x": 0,
        "y": 12
      },
      "id": 54,
      "panels": [
        {
          "aliasColors": {},
          "bars": false,
          "datasource": null,
          "editable": true,
          "error": false,
          "fill": 0,
          "grid": {},
          "gridPos": {
            "h": 7,
            "w": 24,
            "x": 0,
            "y": 13
          },
          "id": 35,
          "isNew": true,
          "legend": {
            "avg": false,
            "current": false,
            "max": false,
            "min": false,
            "show": false,
            "total": false,
            "values": false
          },
          "lines": true,
          "linewidth": 2,
          "links": [],
          "nullPointMode": "connected",
          "percentage": false,
          "pointradius": 5,
          "points": false,
          "renderer": "flot",
          "seriesOverrides": [],
          "stack": false,
          "steppedLine": false,
          "targets": [
            {
              "aggregator": "avg",
              "alias": "load_five_minutes",
              "app": "HOST",
              "downsampleAggregator": "avg",
              "errors": {},
              "metric": "load_five",
              "precision": "default",
              "refId": "B",
              "templatedHost": ""
            }
          ],
          "thresholds": [],
          "timeFrom": null,
          "timeShift": null,
          "title": "System Load Average - 5 Minutes",
          "tooltip": {
            "shared": false,
            "value_type": "cumulative"
          },
          "type": "graph",
          "xaxis": {
            "show": true
          },
          "yaxes": [
            {
              "format": "short",
              "logBase": 1,
              "max": null,
              "min": null,
              "show": true
            },
            {
              "format": "short",
              "logBase": 1,
              "max": null,
              "min": null,
              "show": true
            }
          ]
        }
      ],
      "title": "System Load - 5 Minute",
      "type": "row"
    },
    {
      "collapsed": true,
      "datasource": null,
      "gridPos": {
        "h": 1,
        "w": 24,
        "x": 0,
        "y": 13
      },
      "id": 55,
      "panels": [
        {
          "aliasColors": {},
          "bars": false,
          "datasource": null,
          "editable": true,
          "error": false,
          "fill": 0,
          "grid": {},
          "gridPos": {
            "h": 7,
            "w": 24,
            "x": 0,
            "y": 14
          },
          "id": 36,
          "isNew": true,
          "legend": {
            "avg": false,
            "current": false,
            "max": false,
            "min": false,
            "show": false,
            "total": false,
            "values": false
          },
          "lines": true,
          "linewidth": 2,
          "links": [],
          "nullPointMode": "connected",
          "percentage": false,
          "pointradius": 5,
          "points": false,
          "renderer": "flot",
          "seriesOverrides": [],
          "stack": false,
          "steppedLine": false,
          "targets": [
            {
              "aggregator": "avg",
              "alias": "load_fifteen_minutes",
              "app": "HOST",
              "downsampleAggregator": "avg",
              "errors": {},
              "metric": "load_fifteen",
              "precision": "default",
              "refId": "C",
              "templatedHost": ""
            }
          ],
          "thresholds": [],
          "timeFrom": null,
          "timeShift": null,
          "title": "System Load Average - 15 Minutes",
          "tooltip": {
            "shared": false,
            "value_type": "cumulative"
          },
          "type": "graph",
          "xaxis": {
            "show": true
          },
          "yaxes": [
            {
              "format": "short",
              "logBase": 1,
              "max": null,
              "min": null,
              "show": true
            },
            {
              "format": "short",
              "logBase": 1,
              "max": null,
              "min": null,
              "show": true
            }
          ]
        }
      ],
      "title": "System Load - 15 Minute",
      "type": "row"
    },
    {
      "collapsed": true,
      "datasource": null,
      "gridPos": {
        "h": 1,
        "w": 24,
        "x": 0,
        "y": 14
      },
      "id": 56,
      "panels": [
        {
          "aliasColors": {},
          "bars": false,
          "datasource": null,
          "editable": true,
          "error": false,
          "fill": 0,
          "grid": {},
          "gridPos": {
            "h": 7,
            "w": 12,
            "x": 0,
            "y": 15
          },
          "id": 7,
          "isNew": true,
          "legend": {
            "avg": false,
            "current": false,
            "max": false,
            "min": false,
            "show": false,
            "total": false,
            "values": false
          },
          "lines": true,
          "linewidth": 2,
          "links": [],
          "nullPointMode": "connected",
          "percentage": false,
          "pointradius": 5,
          "points": false,
          "renderer": "flot",
          "seriesOverrides": [],
          "stack": false,
          "steppedLine": false,
          "targets": [
            {
              "aggregator": "avg",
              "app": "HOST",
              "downsampleAggregator": "avg",
              "errors": {},
              "metric": "mem_total",
              "precision": "default",
              "refId": "A",
              "templatedHost": ""
            }
          ],
          "thresholds": [],
          "timeFrom": null,
          "timeShift": null,
          "title": "Memory - Total",
          "tooltip": {
            "shared": false,
            "value_type": "individual"
          },
          "type": "graph",
          "xaxis": {
            "show": true
          },
          "yaxes": [
            {
              "format": "kbytes",
              "logBase": 1,
              "max": null,
              "min": null,
              "show": true
            },
            {
              "format": "short",
              "logBase": 1,
              "max": null,
              "min": null,
              "show": true
            }
          ]
        },
        {
          "aliasColors": {},
          "bars": false,
          "datasource": null,
          "editable": true,
          "error": false,
          "fill": 0,
          "grid": {},
          "gridPos": {
            "h": 7,
            "w": 12,
            "x": 12,
            "y": 15
          },
          "id": 39,
          "isNew": true,
          "legend": {
            "avg": false,
            "current": false,
            "max": false,
            "min": false,
            "show": false,
            "total": false,
            "values": false
          },
          "lines": true,
          "linewidth": 2,
          "links": [],
          "nullPointMode": "connected",
          "percentage": false,
          "pointradius": 5,
          "points": false,
          "renderer": "flot",
          "seriesOverrides": [],
          "stack": false,
          "steppedLine": false,
          "targets": [
            {
              "aggregator": "avg",
              "app": "HOST",
              "downsampleAggregator": "avg",
              "errors": {},
              "metric": "mem_used",
              "precision": "default",
              "refId": "A",
              "templatedHost": ""
            }
          ],
          "thresholds": [],
          "timeFrom": null,
          "timeShift": null,
          "title": "Memory - Used",
          "tooltip": {
            "shared": false,
            "value_type": "individual"
          },
          "type": "graph",
          "xaxis": {
            "show": true
          },
          "yaxes": [
            {
              "format": "kbytes",
              "logBase": 1,
              "max": null,
              "min": null,
              "show": true
            },
            {
              "format": "short",
              "logBase": 1,
              "max": null,
              "min": null,
              "show": true
            }
          ]
        }
      ],
      "title": "Memory - Total / Used",
      "type": "row"
    },
    {
      "collapsed": true,
      "datasource": null,
      "gridPos": {
        "h": 1,
        "w": 24,
        "x": 0,
        "y": 15
      },
      "id": 57,
      "panels": [
        {
          "aliasColors": {},
          "bars": false,
          "datasource": null,
          "editable": true,
          "error": false,
          "fill": 0,
          "grid": {},
          "gridPos": {
            "h": 7,
            "w": 12,
            "x": 0,
            "y": 16
          },
          "id": 37,
          "isNew": true,
          "legend": {
            "avg": false,
            "current": false,
            "max": false,
            "min": false,
            "show": false,
            "total": false,
            "values": false
          },
          "lines": true,
          "linewidth": 2,
          "links": [],
          "nullPointMode": "connected",
          "percentage": false,
          "pointradius": 5,
          "points": false,
          "renderer": "flot",
          "seriesOverrides": [],
          "stack": false,
          "steppedLine": false,
          "targets": [
            {
              "aggregator": "avg",
              "app": "HOST",
              "downsampleAggregator": "avg",
              "errors": {},
              "metric": "mem_free",
              "precision": "default",
              "refId": "B",
              "templatedHost": ""
            }
          ],
          "thresholds": [],
          "timeFrom": null,
          "timeShift": null,
          "title": "Memory - Free",
          "tooltip": {
            "shared": false,
            "value_type": "individual"
          },
          "type": "graph",
          "xaxis": {
            "show": true
          },
          "yaxes": [
            {
              "format": "kbytes",
              "logBase": 1,
              "max": null,
              "min": null,
              "show": true
            },
            {
              "format": "short",
              "logBase": 1,
              "max": null,
              "min": null,
              "show": true
            }
          ]
        },
        {
          "aliasColors": {},
          "bars": false,
          "datasource": null,
          "editable": true,
          "error": false,
          "fill": 0,
          "grid": {},
          "gridPos": {
            "h": 7,
            "w": 12,
            "x": 12,
            "y": 16
          },
          "id": 38,
          "isNew": true,
          "legend": {
            "avg": false,
            "current": false,
            "max": false,
            "min": false,
            "show": false,
            "total": false,
            "values": false
          },
          "lines": true,
          "linewidth": 2,
          "links": [],
          "nullPointMode": "connected",
          "percentage": false,
          "pointradius": 5,
          "points": false,
          "renderer": "flot",
          "seriesOverrides": [
            {
              "alias": "mem_cached",
              "stack": false
            },
            {
              "alias": "mem_buffered",
              "stack": false
            },
            {
              "alias": "mem_shared",
              "stack": false
            }
          ],
          "stack": false,
          "steppedLine": false,
          "targets": [
            {
              "aggregator": "avg",
              "app": "HOST",
              "downsampleAggregator": "avg",
              "errors": {},
              "metric": "mem_cached",
              "precision": "default",
              "refId": "C",
              "templatedHost": ""
            }
          ],
          "thresholds": [],
          "timeFrom": null,
          "timeShift": null,
          "title": "Memory - Cached",
          "tooltip": {
            "shared": false,
            "value_type": "individual"
          },
          "type": "graph",
          "xaxis": {
            "show": true
          },
          "yaxes": [
            {
              "format": "kbytes",
              "logBase": 1,
              "max": null,
              "min": null,
              "show": true
            },
            {
              "format": "short",
              "logBase": 1,
              "max": null,
              "min": null,
              "show": true
            }
          ]
        }
      ],
      "title": "Memory - Free / Cached",
      "type": "row"
    },
    {
      "collapsed": true,
      "datasource": null,
      "gridPos": {
        "h": 1,
        "w": 24,
        "x": 0,
        "y": 16
      },
      "id": 58,
      "panels": [
        {
          "aliasColors": {},
          "bars": false,
          "datasource": null,
          "editable": true,
          "error": false,
          "fill": 0,
          "grid": {},
          "gridPos": {
            "h": 7,
            "w": 12,
            "x": 0,
            "y": 17
          },
          "id": 40,
          "isNew": true,
          "legend": {
            "avg": false,
            "current": false,
            "max": false,
            "min": false,
            "show": false,
            "total": false,
            "values": false
          },
          "lines": true,
          "linewidth": 2,
          "links": [],
          "nullPointMode": "connected",
          "percentage": false,
          "pointradius": 5,
          "points": false,
          "renderer": "flot",
          "seriesOverrides": [
            {
              "alias": "mem_cached",
              "stack": false
            },
            {
              "alias": "mem_buffered",
              "stack": false
            },
            {
              "alias": "mem_shared",
              "stack": false
            }
          ],
          "stack": false,
          "steppedLine": false,
          "targets": [
            {
              "aggregator": "avg",
              "app": "HOST",
              "downsampleAggregator": "avg",
              "errors": {},
              "metric": "mem_buffered",
              "precision": "default",
              "refId": "D",
              "templatedHost": ""
            }
          ],
          "thresholds": [],
          "timeFrom": null,
          "timeShift": null,
          "title": "Memory - Buffered",
          "tooltip": {
            "shared": false,
            "value_type": "individual"
          },
          "type": "graph",
          "xaxis": {
            "show": true
          },
          "yaxes": [
            {
              "format": "kbytes",
              "logBase": 1,
              "max": null,
              "min": null,
              "show": true
            },
            {
              "format": "short",
              "logBase": 1,
              "max": null,
              "min": null,
              "show": true
            }
          ]
        },
        {
          "aliasColors": {},
          "bars": false,
          "datasource": null,
          "editable": true,
          "error": false,
          "fill": 0,
          "grid": {},
          "gridPos": {
            "h": 7,
            "w": 12,
            "x": 12,
            "y": 17
          },
          "id": 41,
          "isNew": true,
          "legend": {
            "avg": false,
            "current": false,
            "max": false,
            "min": false,
            "show": false,
            "total": false,
            "values": false
          },
          "lines": true,
          "linewidth": 2,
          "links": [],
          "nullPointMode": "connected",
          "percentage": false,
          "pointradius": 5,
          "points": false,
          "renderer": "flot",
          "seriesOverrides": [
            {
              "alias": "mem_cached",
              "stack": false
            },
            {
              "alias": "mem_buffered",
              "stack": false
            },
            {
              "alias": "mem_shared",
              "stack": false
            }
          ],
          "stack": false,
          "steppedLine": false,
          "targets": [
            {
              "aggregator": "avg",
              "app": "HOST",
              "downsampleAggregator": "avg",
              "errors": {},
              "metric": "mem_shared",
              "precision": "default",
              "refId": "E",
              "templatedHost": ""
            }
          ],
          "thresholds": [],
          "timeFrom": null,
          "timeShift": null,
          "title": "Memory - Shared",
          "tooltip": {
            "shared": false,
            "value_type": "individual"
          },
          "type": "graph",
          "xaxis": {
            "show": true
          },
          "yaxes": [
            {
              "format": "kbytes",
              "logBase": 1,
              "max": null,
              "min": null,
              "show": true
            },
            {
              "format": "short",
              "logBase": 1,
              "max": null,
              "min": null,
              "show": true
            }
          ]
        }
      ],
      "title": "Memory - Buffered / Shared",
      "type": "row"
    },
    {
      "collapsed": true,
      "datasource": null,
      "gridPos": {
        "h": 1,
        "w": 24,
        "x": 0,
        "y": 17
      },
      "id": 59,
      "panels": [
        {
          "aliasColors": {},
          "bars": false,
          "datasource": null,
          "editable": true,
          "error": false,
          "fill": 0,
          "grid": {},
          "gridPos": {
            "h": 7,
            "w": 12,
            "x": 0,
            "y": 18
          },
          "id": 10,
          "isNew": true,
          "legend": {
            "avg": false,
            "current": false,
            "max": false,
            "min": false,
            "show": false,
            "total": false,
            "values": false
          },
          "lines": true,
          "linewidth": 2,
          "links": [],
          "nullPointMode": "connected",
          "percentage": false,
          "pointradius": 5,
          "points": false,
          "renderer": "flot",
          "seriesOverrides": [],
          "stack": false,
          "steppedLine": false,
          "targets": [
            {
              "aggregator": "avg",
              "app": "HOST",
              "downsampleAggregator": "avg",
              "errors": {},
              "metric": "disk_used",
              "precision": "default",
              "refId": "C",
              "templatedHost": ""
            }
          ],
          "thresholds": [],
          "timeFrom": null,
          "timeShift": null,
          "title": "Disk Used",
          "tooltip": {
            "shared": false,
            "value_type": "individual"
          },
          "type": "graph",
          "xaxis": {
            "show": true
          },
          "yaxes": [
            {
              "format": "gbytes",
              "logBase": 1,
              "max": null,
              "min": null,
              "show": true
            },
            {
              "format": "short",
              "logBase": 1,
              "max": null,
              "min": null,
              "show": true
            }
          ]
        },
        {
          "aliasColors": {},
          "bars": false,
          "datasource": null,
          "editable": true,
          "error": false,
          "fill": 0,
          "grid": {},
          "gridPos": {
            "h": 7,
            "w": 12,
            "x": 12,
            "y": 18
          },
          "id": 42,
          "isNew": true,
          "legend": {
            "avg": false,
            "current": false,
            "max": false,
            "min": false,
            "show": false,
            "total": false,
            "values": false
          },
          "lines": true,
          "linewidth": 2,
          "links": [],
          "nullPointMode": "connected",
          "percentage": false,
          "pointradius": 5,
          "points": false,
          "renderer": "flot",
          "seriesOverrides": [],
          "stack": false,
          "steppedLine": false,
          "targets": [
            {
              "aggregator": "avg",
              "app": "HOST",
              "downsampleAggregator": "avg",
              "errors": {},
              "metric": "disk_free",
              "precision": "default",
              "refId": "C",
              "templatedHost": ""
            }
          ],
          "thresholds": [],
          "timeFrom": null,
          "timeShift": null,
          "title": "Disk Free",
          "tooltip": {
            "shared": false,
            "value_type": "individual"
          },
          "type": "graph",
          "xaxis": {
            "show": true
          },
          "yaxes": [
            {
              "format": "gbytes",
              "logBase": 1,
              "max": null,
              "min": null,
              "show": true
            },
            {
              "format": "short",
              "logBase": 1,
              "max": null,
              "min": null,
              "show": true
            }
          ]
        }
      ],
      "title": "Disk Utilization",
      "type": "row"
    },
    {
      "collapsed": true,
      "datasource": null,
      "gridPos": {
        "h": 1,
        "w": 24,
        "x": 0,
        "y": 18
      },
      "id": 60,
      "panels": [
        {
          "aliasColors": {},
          "bars": false,
          "datasource": null,
          "editable": true,
          "error": false,
          "fill": 0,
          "grid": {},
          "gridPos": {
            "h": 7,
            "w": 12,
            "x": 0,
            "y": 19
          },
          "id": 13,
          "isNew": true,
          "legend": {
            "avg": false,
            "current": false,
            "max": false,
            "min": false,
            "show": false,
            "total": false,
            "values": false
          },
          "lines": true,
          "linewidth": 2,
          "links": [],
          "nullPointMode": "connected",
          "percentage": false,
          "pointradius": 5,
          "points": false,
          "renderer": "flot",
          "seriesOverrides": [],
          "stack": false,
          "steppedLine": false,
          "targets": [
            {
              "aggregator": "avg",
              "app": "HOST",
              "downsampleAggregator": "avg",
              "errors": {},
              "hosts": "",
              "metric": "read_bytes",
              "precision": "default",
              "refId": "C",
              "templatedHost": "",
              "transform": "rate"
            }
          ],
          "thresholds": [],
          "timeFrom": null,
          "timeShift": null,
          "title": "Read Bytes",
          "tooltip": {
            "shared": false,
            "value_type": "cumulative"
          },
          "type": "graph",
          "xaxis": {
            "show": true
          },
          "yaxes": [
            {
              "format": "Bps",
              "logBase": 1,
              "max": null,
              "min": null,
              "show": true
            },
            {
              "format": "Bps",
              "logBase": 1,
              "max": null,
              "min": null,
              "show": true
            }
          ]
        },
        {
          "aliasColors": {},
          "bars": false,
          "datasource": null,
          "editable": true,
          "error": false,
          "fill": 0,
          "grid": {},
          "gridPos": {
            "h": 7,
            "w": 12,
            "x": 12,
            "y": 19
          },
          "id": 48,
          "isNew": true,
          "legend": {
            "avg": false,
            "current": false,
            "max": false,
            "min": false,
            "show": false,
            "total": false,
            "values": false
          },
          "lines": true,
          "linewidth": 2,
          "links": [],
          "nullPointMode": "connected",
          "percentage": false,
          "pointradius": 5,
          "points": false,
          "renderer": "flot",
          "seriesOverrides": [],
          "stack": false,
          "steppedLine": false,
          "targets": [
            {
              "aggregator": "avg",
              "app": "HOST",
              "downsampleAggregator": "avg",
              "errors": {},
              "hosts": "",
              "metric": "write_bytes",
              "precision": "default",
              "refId": "D",
              "templatedHost": "",
              "transform": "rate"
            }
          ],
          "thresholds": [],
          "timeFrom": null,
          "timeShift": null,
          "title": "Write Bytes",
          "tooltip": {
            "shared": false,
            "value_type": "cumulative"
          },
          "type": "graph",
          "xaxis": {
            "show": true
          },
          "yaxes": [
            {
              "format": "Bps",
              "logBase": 1,
              "max": null,
              "min": null,
              "show": true
            },
            {
              "format": "Bps",
              "logBase": 1,
              "max": null,
              "min": null,
              "show": true
            }
          ]
        }
      ],
      "title": "Disk IO",
      "type": "row"
    },
    {
      "collapsed": true,
      "datasource": null,
      "gridPos": {
        "h": 1,
        "w": 24,
        "x": 0,
        "y": 19
      },
      "id": 61,
      "panels": [
        {
          "aliasColors": {},
          "bars": false,
          "datasource": null,
          "editable": true,
          "error": false,
          "fill": 0,
          "grid": {},
          "gridPos": {
            "h": 7,
            "w": 12,
            "x": 0,
            "y": 20
          },
          "id": 12,
          "isNew": true,
          "legend": {
            "avg": false,
            "current": false,
            "max": false,
            "min": false,
            "show": false,
            "total": false,
            "values": false
          },
          "lines": true,
          "linewidth": 2,
          "links": [],
          "nullPointMode": "connected",
          "percentage": false,
          "pointradius": 5,
          "points": false,
          "renderer": "flot",
          "seriesOverrides": [],
          "stack": false,
          "steppedLine": false,
          "targets": [
            {
              "aggregator": "avg",
              "app": "HOST",
              "downsampleAggregator": "avg",
              "errors": {},
              "hosts": "",
              "metric": "read_count",
              "precision": "default",
              "refId": "A",
              "templatedHost": "",
              "transform": "rate"
            }
          ],
          "thresholds": [],
          "timeFrom": null,
          "timeShift": null,
          "title": "Read Count",
          "tooltip": {
            "shared": false,
            "value_type": "cumulative"
          },
          "type": "graph",
          "xaxis": {
            "show": true
          },
          "yaxes": [
            {
              "format": "rps",
              "logBase": 1,
              "max": null,
              "min": null,
              "show": true
            },
            {
              "format": "Bps",
              "logBase": 1,
              "max": null,
              "min": null,
              "show": true
            }
          ]
        },
        {
          "aliasColors": {},
          "bars": false,
          "datasource": null,
          "editable": true,
          "error": false,
          "fill": 0,
          "grid": {},
          "gridPos": {
            "h": 7,
            "w": 12,
            "x": 12,
            "y": 20
          },
          "id": 47,
          "isNew": true,
          "legend": {
            "avg": false,
            "current": false,
            "max": false,
            "min": false,
            "show": false,
            "total": false,
            "values": false
          },
          "lines": true,
          "linewidth": 2,
          "links": [],
          "nullPointMode": "connected",
          "percentage": false,
          "pointradius": 5,
          "points": false,
          "renderer": "flot",
          "seriesOverrides": [],
          "stack": false,
          "steppedLine": false,
          "targets": [
            {
              "aggregator": "avg",
              "app": "HOST",
              "downsampleAggregator": "avg",
              "errors": {},
              "hosts": "",
              "metric": "write_count",
              "precision": "default",
              "refId": "B",
              "templatedHost": "",
              "transform": "rate"
            }
          ],
          "thresholds": [],
          "timeFrom": null,
          "timeShift": null,
          "title": "Write Count",
          "tooltip": {
            "shared": false,
            "value_type": "cumulative"
          },
          "type": "graph",
          "xaxis": {
            "show": true
          },
          "yaxes": [
            {
              "format": "wps",
              "logBase": 1,
              "max": null,
              "min": null,
              "show": true
            },
            {
              "format": "Bps",
              "logBase": 1,
              "max": null,
              "min": null,
              "show": true
            }
          ]
        }
      ],
      "title": "Disk IOPS",
      "type": "row"
    },
    {
      "collapsed": true,
      "datasource": null,
      "gridPos": {
        "h": 1,
        "w": 24,
        "x": 0,
        "y": 20
      },
      "id": 62,
      "panels": [
        {
          "aliasColors": {},
          "bars": false,
          "datasource": null,
          "editable": true,
          "error": false,
          "fill": 0,
          "grid": {},
          "gridPos": {
            "h": 7,
            "w": 12,
            "x": 0,
            "y": 21
          },
          "id": 25,
          "isNew": true,
          "legend": {
            "avg": false,
            "current": false,
            "max": false,
            "min": false,
            "show": false,
            "total": false,
            "values": false
          },
          "lines": true,
          "linewidth": 2,
          "links": [],
          "nullPointMode": "connected",
          "percentage": false,
          "pointradius": 5,
          "points": false,
          "renderer": "flot",
          "seriesOverrides": [],
          "stack": false,
          "steppedLine": false,
          "targets": [
            {
              "aggregator": "avg",
              "app": "HOST",
              "downsampleAggregator": "avg",
              "errors": {},
              "metric": "bytes_in",
              "precision": "default",
              "refId": "A",
              "templatedHost": ""
            }
          ],
          "thresholds": [],
          "timeFrom": null,
          "timeShift": null,
          "title": "Network Bytes Received",
          "tooltip": {
            "shared": false,
            "value_type": "cumulative"
          },
          "type": "graph",
          "xaxis": {
            "show": true
          },
          "yaxes": [
            {
              "format": "Bps",
              "logBase": 1,
              "max": null,
              "min": null,
              "show": true
            },
            {
              "format": "short",
              "logBase": 1,
              "max": null,
              "min": null,
              "show": true
            }
          ]
        },
        {
          "aliasColors": {},
          "bars": false,
          "datasource": null,
          "editable": true,
          "error": false,
          "fill": 0,
          "grid": {},
          "gridPos": {
            "h": 7,
            "w": 12,
            "x": 12,
            "y": 21
          },
          "id": 43,
          "isNew": true,
          "legend": {
            "avg": false,
            "current": false,
            "max": false,
            "min": false,
            "show": false,
            "total": false,
            "values": false
          },
          "lines": true,
          "linewidth": 2,
          "links": [],
          "nullPointMode": "connected",
          "percentage": false,
          "pointradius": 5,
          "points": false,
          "renderer": "flot",
          "seriesOverrides": [],
          "stack": false,
          "steppedLine": false,
          "targets": [
            {
              "aggregator": "avg",
              "app": "HOST",
              "downsampleAggregator": "avg",
              "errors": {},
              "metric": "bytes_out",
              "precision": "default",
              "refId": "B",
              "templatedHost": ""
            }
          ],
          "thresholds": [],
          "timeFrom": null,
          "timeShift": null,
          "title": "Network Bytes Sent",
          "tooltip": {
            "shared": false,
            "value_type": "cumulative"
          },
          "type": "graph",
          "xaxis": {
            "show": true
          },
          "yaxes": [
            {
              "format": "Bps",
              "logBase": 1,
              "max": null,
              "min": null,
              "show": true
            },
            {
              "format": "short",
              "logBase": 1,
              "max": null,
              "min": null,
              "show": true
            }
          ]
        }
      ],
      "title": "Network IO",
      "type": "row"
    },
    {
      "collapsed": true,
      "datasource": null,
      "gridPos": {
        "h": 1,
        "w": 24,
        "x": 0,
        "y": 21
      },
      "id": 63,
      "panels": [
        {
          "aliasColors": {},
          "bars": false,
          "datasource": null,
          "editable": true,
          "error": false,
          "fill": 0,
          "grid": {},
          "gridPos": {
            "h": 7,
            "w": 12,
            "x": 0,
            "y": 22
          },
          "id": 27,
          "isNew": true,
          "legend": {
            "avg": false,
            "current": false,
            "max": false,
            "min": false,
            "show": false,
            "total": false,
            "values": false
          },
          "lines": true,
          "linewidth": 2,
          "links": [],
          "nullPointMode": "connected",
          "percentage": false,
          "pointradius": 5,
          "points": false,
          "renderer": "flot",
          "seriesOverrides": [],
          "stack": false,
          "steppedLine": false,
          "targets": [
            {
              "aggregator": "avg",
              "app": "HOST",
              "downsampleAggregator": "avg",
              "errors": {},
              "hosts": "",
              "metric": "pkts_in",
              "precision": "default",
              "refId": "A",
              "templatedHost": ""
            }
          ],
          "thresholds": [],
          "timeFrom": null,
          "timeShift": null,
          "title": "Network Packets Received",
          "tooltip": {
            "shared": false,
            "value_type": "cumulative"
          },
          "type": "graph",
          "xaxis": {
            "show": true
          },
          "yaxes": [
            {
              "format": "pps",
              "logBase": 1,
              "max": null,
              "min": null,
              "show": true
            },
            {
              "format": "short",
              "logBase": 1,
              "max": null,
              "min": null,
              "show": true
            }
          ]
        },
        {
          "aliasColors": {},
          "bars": false,
          "datasource": null,
          "editable": true,
          "error": false,
          "fill": 0,
          "grid": {},
          "gridPos": {
            "h": 7,
            "w": 12,
            "x": 12,
            "y": 22
          },
          "id": 44,
          "isNew": true,
          "legend": {
            "avg": false,
            "current": false,
            "max": false,
            "min": false,
            "show": false,
            "total": false,
            "values": false
          },
          "lines": true,
          "linewidth": 2,
          "links": [],
          "nullPointMode": "connected",
          "percentage": false,
          "pointradius": 5,
          "points": false,
          "renderer": "flot",
          "seriesOverrides": [],
          "stack": false,
          "steppedLine": false,
          "targets": [
            {
              "aggregator": "avg",
              "app": "HOST",
              "downsampleAggregator": "avg",
              "errors": {},
              "hosts": "",
              "metric": "pkts_out",
              "precision": "default",
              "refId": "B",
              "templatedHost": ""
            }
          ],
          "thresholds": [],
          "timeFrom": null,
          "timeShift": null,
          "title": "Network Packets Sent",
          "tooltip": {
            "shared": false,
            "value_type": "cumulative"
          },
          "type": "graph",
          "xaxis": {
            "show": true
          },
          "yaxes": [
            {
              "format": "pps",
              "logBase": 1,
              "max": null,
              "min": null,
              "show": true
            },
            {
              "format": "short",
              "logBase": 1,
              "max": null,
              "min": null,
              "show": true
            }
          ]
        }
      ],
      "title": "Network Packets",
      "type": "row"
    },
    {
      "collapsed": true,
      "datasource": null,
      "gridPos": {
        "h": 1,
        "w": 24,
        "x": 0,
        "y": 22
      },
      "id": 64,
      "panels": [
        {
          "aliasColors": {},
          "bars": false,
          "datasource": null,
          "editable": true,
          "error": false,
          "fill": 0,
          "grid": {},
          "gridPos": {
            "h": 7,
            "w": 12,
            "x": 0,
            "y": 23
          },
          "id": 9,
          "isNew": true,
          "legend": {
            "avg": false,
            "current": false,
            "max": false,
            "min": false,
            "show": false,
            "total": false,
            "values": false
          },
          "lines": true,
          "linewidth": 2,
          "links": [],
          "nullPointMode": "connected",
          "percentage": false,
          "pointradius": 5,
          "points": false,
          "renderer": "flot",
          "seriesOverrides": [],
          "stack": false,
          "steppedLine": false,
          "targets": [
            {
              "aggregator": "avg",
              "app": "HOST",
              "downsampleAggregator": "avg",
              "errors": {},
              "metric": "swap_total",
              "precision": "default",
              "refId": "B",
              "templatedHost": ""
            }
          ],
          "thresholds": [],
          "timeFrom": null,
          "timeShift": null,
          "title": "Swap Space - Total",
          "tooltip": {
            "shared": false,
            "value_type": "cumulative"
          },
          "type": "graph",
          "xaxis": {
            "show": true
          },
          "yaxes": [
            {
              "format": "kbytes",
              "logBase": 1,
              "max": null,
              "min": null,
              "show": true
            },
            {
              "format": "short",
              "logBase": 1,
              "max": null,
              "min": null,
              "show": true
            }
          ]
        },
        {
          "aliasColors": {},
          "bars": false,
          "datasource": null,
          "editable": true,
          "error": false,
          "fill": 0,
          "grid": {},
          "gridPos": {
            "h": 7,
            "w": 12,
            "x": 12,
            "y": 23
          },
          "id": 45,
          "isNew": true,
          "legend": {
            "avg": false,
            "current": false,
            "max": false,
            "min": false,
            "show": false,
            "total": false,
            "values": false
          },
          "lines": true,
          "linewidth": 2,
          "links": [],
          "nullPointMode": "connected",
          "percentage": false,
          "pointradius": 5,
          "points": false,
          "renderer": "flot",
          "seriesOverrides": [],
          "stack": false,
          "steppedLine": false,
          "targets": [
            {
              "aggregator": "avg",
              "app": "HOST",
              "downsampleAggregator": "avg",
              "errors": {},
              "metric": "swap_free",
              "precision": "default",
              "refId": "A",
              "templatedHost": ""
            }
          ],
          "thresholds": [],
          "timeFrom": null,
          "timeShift": null,
          "title": "Swap Space - Free",
          "tooltip": {
            "shared": false,
            "value_type": "cumulative"
          },
          "type": "graph",
          "xaxis": {
            "show": true
          },
          "yaxes": [
            {
              "format": "kbytes",
              "logBase": 1,
              "max": null,
              "min": null,
              "show": true
            },
            {
              "format": "short",
              "logBase": 1,
              "max": null,
              "min": null,
              "show": true
            }
          ]
        }
      ],
      "title": "Swap",
      "type": "row"
    },
    {
      "collapsed": true,
      "datasource": null,
      "gridPos": {
        "h": 1,
        "w": 24,
        "x": 0,
        "y": 23
      },
      "id": 65,
      "panels": [
        {
          "aliasColors": {},
          "bars": false,
          "datasource": null,
          "editable": true,
          "error": false,
          "fill": 0,
          "grid": {},
          "gridPos": {
            "h": 7,
            "w": 12,
            "x": 0,
            "y": 24
          },
          "id": 24,
          "isNew": true,
          "legend": {
            "avg": false,
            "current": false,
            "max": false,
            "min": false,
            "show": false,
            "total": false,
            "values": false
          },
          "lines": true,
          "linewidth": 2,
          "links": [],
          "nullPointMode": "connected",
          "percentage": false,
          "pointradius": 5,
          "points": false,
          "renderer": "flot",
          "seriesOverrides": [],
          "stack": false,
          "steppedLine": false,
          "targets": [
            {
              "aggregator": "avg",
              "app": "HOST",
              "downsampleAggregator": "avg",
              "errors": {},
              "metric": "proc_total",
              "precision": "default",
              "refId": "B",
              "templatedHost": ""
            }
          ],
          "thresholds": [],
          "timeFrom": null,
          "timeShift": null,
          "title": "Num Processes - Total",
          "tooltip": {
            "shared": false,
            "value_type": "cumulative"
          },
          "type": "graph",
          "xaxis": {
            "show": true
          },
          "yaxes": [
            {
              "format": "short",
              "logBase": 1,
              "max": null,
              "min": null,
              "show": true
            },
            {
              "format": "short",
              "logBase": 1,
              "max": null,
              "min": null,
              "show": true
            }
          ]
        },
        {
          "aliasColors": {},
          "bars": false,
          "datasource": null,
          "editable": true,
          "error": false,
          "fill": 0,
          "grid": {},
          "gridPos": {
            "h": 7,
            "w": 12,
            "x": 12,
            "y": 24
          },
          "id": 46,
          "isNew": true,
          "legend": {
            "avg": false,
            "current": false,
            "max": false,
            "min": false,
            "show": false,
            "total": false,
            "values": false
          },
          "lines": true,
          "linewidth": 2,
          "links": [],
          "nullPointMode": "connected",
          "percentage": false,
          "pointradius": 5,
          "points": false,
          "renderer": "flot",
          "seriesOverrides": [],
          "stack": false,
          "steppedLine": false,
          "targets": [
            {
              "aggregator": "max",
              "app": "HOST",
              "downsampleAggregator": "avg",
              "errors": {},
              "metric": "proc_run",
              "precision": "default",
              "refId": "A",
              "templatedHost": ""
            }
          ],
          "thresholds": [],
          "timeFrom": null,
          "timeShift": null,
          "title": "Num Processes - Runnable",
          "tooltip": {
            "shared": false,
            "value_type": "cumulative"
          },
          "type": "graph",
          "xaxis": {
            "show": true
          },
          "yaxes": [
            {
              "format": "short",
              "logBase": 1,
              "max": null,
              "min": null,
              "show": true
            },
            {
              "format": "short",
              "logBase": 1,
              "max": null,
              "min": null,
              "show": true
            }
          ]
        }
      ],
      "title": "Num Processes",
      "type": "row"
    }
  ],
  "refresh": false,
  "schemaVersion": 22,
  "style": "dark",
  "tags": [
    "system"
  ],
  "templating": {
    "list": [
      {
        "allFormat": "glob",
        "allValue": null,
        "current": {
          "text": "HOST",
          "value": "HOST"
        },
        "datasource": null,
        "hide": 1,
        "hideLabel": true,
        "includeAll": false,
        "label": "",
        "multi": false,
        "multiFormat": "glob",
        "name": "components",
        "options": [
          {
            "selected": true,
            "text": "HOST",
            "value": "HOST"
          }
        ],
        "query": "HOST",
        "refresh": 0,
        "skipUrlSync": false,
        "type": "custom"
      },
      {
        "allFormat": "glob",
        "allValue": null,
        "current": {
          "selected": false,
          "text": "All",
          "value": "$__all"
        },
        "datasource": null,
        "definition": "",
        "hide": 0,
        "includeAll": true,
        "index": -1,
        "label": "Hosts",
        "multi": true,
        "multiFormat": "glob",
        "name": "hosts",
        "options": [],
        "query": "hosts.$cluster",
        "refresh": 1,
        "regex": "",
        "skipUrlSync": false,
        "sort": 0,
        "tagValuesQuery": "",
        "tags": [],
        "tagsQuery": "",
        "type": "query",
        "useTags": false
      },
      {
        "allFormat": "glob",
        "allValue": null,
        "current": {
          "text": "top",
          "value": "top"
        },
        "datasource": null,
        "hide": 0,
        "hideLabel": false,
        "includeAll": false,
        "label": "show",
        "multi": false,
        "multiFormat": "glob",
        "name": "orientation",
        "options": [
          {
            "selected": true,
            "text": "top",
            "value": "top"
          },
          {
            "selected": false,
            "text": "bottom",
            "value": "bottom"
          }
        ],
        "query": "top,bottom",
        "refresh": 0,
        "skipUrlSync": false,
        "type": "custom"
      },
      {
        "allFormat": "glob",
        "allValue": null,
        "current": {
          "text": "20",
          "value": "20"
        },
        "datasource": null,
        "hide": 1,
        "hideLabel": true,
        "includeAll": false,
        "label": "instances",
        "multi": false,
        "multiFormat": "glob",
        "name": "instances",
        "options": [
          {
            "selected": true,
            "text": "20",
            "value": "20"
          },
          {
            "selected": false,
            "text": "1",
            "value": "1"
          },
          {
            "selected": false,
            "text": "5",
            "value": "5"
          },
          {
            "selected": false,
            "text": "10",
            "value": "10"
          },
          {
            "selected": false,
            "text": "15",
            "value": "15"
          },
          {
            "selected": false,
            "text": "50",
            "value": "50"
          },
          {
            "selected": false,
            "text": "100",
            "value": "100"
          }
        ],
        "query": "20,1,5,10,15,50,100",
        "refresh": 0,
        "skipUrlSync": false,
        "type": "custom"
      },
      {
        "allFormat": "glob",
        "allValue": null,
        "current": {
          "text": "avg",
          "value": "avg"
        },
        "datasource": null,
        "hide": 0,
        "includeAll": false,
        "label": "aggregator",
        "multi": false,
        "multiFormat": "glob",
        "name": "topagg",
        "options": [
          {
            "selected": true,
            "text": "avg",
            "value": "avg"
          },
          {
            "selected": false,
            "text": "max",
            "value": "max"
          },
          {
            "selected": false,
            "text": "sum",
            "value": "sum"
          }
        ],
        "query": "avg,max,sum",
        "refresh": 0,
        "skipUrlSync": false,
        "type": "custom"
      }
    ]
  },
  "time": {
    "from": "now-6h",
    "to": "now"
  },
  "timepicker": {
    "now": true,
    "refresh_intervals": [
      "5s",
      "10s",
      "30s",
      "1m",
      "5m",
      "15m",
      "30m",
      "1h",
      "2h",
      "1d"
    ],
    "time_options": [
      "5m",
      "15m",
      "1h",
      "6h",
      "12h",
      "24h",
      "2d",
      "7d",
      "30d"
    ]
  },
  "timezone": "browser",
  "title": "System - Servers",
  "uid": "vU1iCXT7z",
  "variables": {
    "list": []
  },
  "version": 2
}